dify_client/__init__.py
dify_client/client.py
dify_cli_qst-0.1.12.dist-info/LICENSE
dify_cli_qst-0.1.12.dist-info/METADATA
dify_cli_qst-0.1.12.dist-info/WHEEL
dify_cli_qst-0.1.12.dist-info/top_level.txt
dify_cli_qst-0.1.12.dist-info/RECORD
