Metadata-Version: 2.1
Name: dify-cli-qst
Version: 0.1.12
Summary: A package for interacting with the Dify Service-API
Home-page: https://github.com/langgenius/dify
Author: qdyujiang002
Author-email: 501540155@qq.com
License: MIT
Keywords: dify nlp ai language-processing
Classifier: Programming Language :: Python :: 3
Classifier: License :: OSI Approved :: MIT License
Classifier: Operating System :: OS Independent
Requires-Python: >=3.6
License-File: LICENSE
Requires-Dist: requests
